toolhub/__init__.py
toolhub/config.py
toolhub/demo/__init__.py
toolhub/demo/call_tools.py
toolhub/demo/openai_assistant.py
toolhub/demo/openai_chat.py
toolhub/demo/utils.py
toolhub/integrations/__init__.py
toolhub/integrations/openapi/__init__.py
toolhub/integrations/openapi/apis/__init__.py
toolhub/integrations/openapi/apis/crunchbase/crunchbase.py
toolhub/integrations/openapi/apis/crunchbase/crunchbase_v4.json
toolhub/integrations/openapi/client.py
toolhub/integrations/openapi/function.py
toolhub/integrations/openapi/parser.py
toolhub/integrations/openapi/provider.py
toolhub/integrations/rapidapi/__init__.py
toolhub/integrations/rapidapi/execute.py
toolhub/integrations/rapidapi/function.py
toolhub/integrations/rapidapi/functions.json
toolhub/integrations/rapidapi/get_collection_name.py
toolhub/integrations/rapidapi/loader.py
toolhub/integrations/rapidapi/private/__init__.py
toolhub/integrations/rapidapi/private/ast-grep.yaml
toolhub/integrations/rapidapi/private/extract_funcs.sh
toolhub/integrations/rapidapi/private/function_infos.json
toolhub/integrations/rapidapi/private/generate_functions_json.py
toolhub/integrations/rapidapi/private/json_parser.py
toolhub/integrations/rapidapi/provider.py
toolhub/integrations/rapidapi/utils.py
toolhub/lib/__init__.py
toolhub/lib/auth.py
toolhub/lib/function.py
toolhub/lib/functions/__init__.py
toolhub/lib/hub.py
toolhub/lib/provider.py
toolhub/lib/registry.py
toolhub/lib/utils.py
toolhub/openai/__init__.py
toolhub/openai/assistant_utils.py
toolhub/openai/openai_assistant_hub.py
toolhub/openai/openai_chat_hub.py
toolhub/openai/utils.py
toolhub/standard_providers/__init__.py
toolhub/standard_providers/random_provider.py
toolhub/standard_providers/tests/test_provider.py
toolhub-0.1.0.dist-info/LICENSE
toolhub-0.1.0.dist-info/METADATA
toolhub-0.1.0.dist-info/WHEEL
toolhub-0.1.0.dist-info/RECORD
