Metadata-Version: 2.1
Name: toolhub
Version: 0.1.0
Summary: A library that manages tools for function-calling LLMs.
Home-page: https://github.com/levrofin/toolhub
License: MIT
Author: Levro
Requires-Python: >=3.10,<4.0
Classifier: License :: OSI Approved :: MIT License
Classifier: Programming Language :: Python :: 3
Classifier: Programming Language :: Python :: 3.10
Classifier: Programming Language :: Python :: 3.11
Requires-Dist: click (==8.1.7)
Requires-Dist: distro (==1.9.0)
Requires-Dist: dynaconf (==3.2.4)
Requires-Dist: httpx (==0.26.0)
Requires-Dist: jsonpickle (==3.0.2)
Requires-Dist: openai (==1.2.1)
Requires-Dist: openapi-python-client (==0.17.2)
Requires-Dist: pydantic (==2.5.3)
Requires-Dist: tenacity (==8.2.3)
Requires-Dist: typing-extensions (>=4.9.0,<5.0.0)
Project-URL: Repository, https://github.com/levrofin/toolhub
